odoo8_addon_mail_compose_select_lang-8.0.1.0.0.99.dev11-py2.7-nspkg.pth
odoo8_addon_mail_compose_select_lang-8.0.1.0.0.99.dev11.dist-info/DESCRIPTION.rst
odoo8_addon_mail_compose_select_lang-8.0.1.0.0.99.dev11.dist-info/METADATA
odoo8_addon_mail_compose_select_lang-8.0.1.0.0.99.dev11.dist-info/RECORD
odoo8_addon_mail_compose_select_lang-8.0.1.0.0.99.dev11.dist-info/WHEEL
odoo8_addon_mail_compose_select_lang-8.0.1.0.0.99.dev11.dist-info/metadata.json
odoo8_addon_mail_compose_select_lang-8.0.1.0.0.99.dev11.dist-info/namespace_packages.txt
odoo8_addon_mail_compose_select_lang-8.0.1.0.0.99.dev11.dist-info/top_level.txt
odoo_addons/mail_compose_select_lang/README.rst
odoo_addons/mail_compose_select_lang/__init__.py
odoo_addons/mail_compose_select_lang/__openerp__.py
odoo_addons/mail_compose_select_lang/i18n/ca.po
odoo_addons/mail_compose_select_lang/i18n/da.po
odoo_addons/mail_compose_select_lang/i18n/de.po
odoo_addons/mail_compose_select_lang/i18n/el_GR.po
odoo_addons/mail_compose_select_lang/i18n/es.po
odoo_addons/mail_compose_select_lang/i18n/es_CO.po
odoo_addons/mail_compose_select_lang/i18n/fr.po
odoo_addons/mail_compose_select_lang/i18n/mail_compose_select_lang.pot
odoo_addons/mail_compose_select_lang/i18n/pt_BR.po
odoo_addons/mail_compose_select_lang/i18n/pt_PT.po
odoo_addons/mail_compose_select_lang/i18n/sl.po
odoo_addons/mail_compose_select_lang/i18n/tr_TR.po
odoo_addons/mail_compose_select_lang/models/__init__.py
odoo_addons/mail_compose_select_lang/models/email_template.py
odoo_addons/mail_compose_select_lang/models/report.py
odoo_addons/mail_compose_select_lang/static/description/icon.png
odoo_addons/mail_compose_select_lang/wizard/__init__.py
odoo_addons/mail_compose_select_lang/wizard/mail_compose_message.py
odoo_addons/mail_compose_select_lang/wizard/mail_compose_message_view.xml
