Metadata-Version: 2.0
Name: odoo8-addon-mail-compose-select-lang
Version: 8.0.1.0.0.99.dev11
Summary: Select language in mail compose window
Home-page: http://www.serviciosbaeza.com
Author: Serv. Tecnol. Avanzados - Pedro M. Baeza, Antiun Ingeniería S.L.,Odoo Community Association (OCA)
Author-email: support@odoo-community.org
License: UNKNOWN
Platform: UNKNOWN
Classifier: Programming Language :: Python
Classifier: Framework :: Odoo
Requires-Python: ~=2.7
Requires-Dist: odoo (<9.0a,>=8.0a)
